contentrules.slack-2.0.2-py3.10-nspkg.pth
contentrules/slack/__init__.py
contentrules/slack/configure.zcml
contentrules/slack/interfaces.py
contentrules/slack/settings.py
contentrules/slack/slack_notifier.py
contentrules/slack/testing.py
contentrules/slack/utils.py
contentrules/slack/actions/__init__.py
contentrules/slack/actions/configure.zcml
contentrules/slack/actions/slack.pt
contentrules/slack/actions/slack.py
contentrules/slack/locales/contentrules.slack.pot
contentrules/slack/locales/update.py
contentrules/slack/locales/de/LC_MESSAGES/contentrules.slack.po
contentrules/slack/locales/en/LC_MESSAGES/contentrules.slack.po
contentrules/slack/locales/es/LC_MESSAGES/contentrules.slack.po
contentrules/slack/locales/pt_BR/LC_MESSAGES/contentrules.slack.po
contentrules.slack-2.0.2.dist-info/LICENSE.GPL
contentrules.slack-2.0.2.dist-info/METADATA
contentrules.slack-2.0.2.dist-info/WHEEL
contentrules.slack-2.0.2.dist-info/entry_points.txt
contentrules.slack-2.0.2.dist-info/namespace_packages.txt
contentrules.slack-2.0.2.dist-info/top_level.txt
contentrules.slack-2.0.2.dist-info/RECORD
