Metadata-Version: 2.1
Name: contentrules.slack
Version: 2.0.2
Summary: Slack content rule action for Plone.
Home-page: https://pypi.python.org/pypi/contentrules.slack
Author: Pendect Tech
Author-email: opensource@pendect.com
License: GPL version 2
Project-URL: PyPI, https://pypi.python.org/pypi/contentrules.slack
Project-URL: Source, https://github.com/collective/contentrules.slack
Project-URL: Tracker, https://github.com/collective/contentrules.slack/issues
Project-URL: Documentation, https://collective.github.io/contentrules.slack
Keywords: Python Plone Slack ContentRules Pendect
Classifier: Development Status :: 5 - Production/Stable
Classifier: Environment :: Web Environment
Classifier: Framework :: Plone
Classifier: Framework :: Plone :: Addon
Classifier: Framework :: Plone :: 6.0
Classifier: Programming Language :: Python
Classifier: Programming Language :: Python :: 3.8
Classifier: Programming Language :: Python :: 3.9
Classifier: Programming Language :: Python :: 3.10
Classifier: Programming Language :: Python :: 3.11
Classifier: Operating System :: OS Independent
Classifier: License :: OSI Approved :: GNU General Public License v2 (GPLv2)
Requires-Python: >=3.8.0
License-File: LICENSE.GPL
Requires-Dist: requests
Requires-Dist: prettyconf
Requires-Dist: Plone
Requires-Dist: setuptools
Requires-Dist: plone.restapi (>=8.34.0)
Provides-Extra: test
Requires-Dist: gocept.pytestlayer ; extra == 'test'
Requires-Dist: plone.app.robotframework[debug] ; extra == 'test'
Requires-Dist: plone.app.testing ; extra == 'test'
Requires-Dist: plone.restapi[test] ; extra == 'test'
Requires-Dist: pytest-cov ; extra == 'test'
Requires-Dist: pytest-plone (>=0.2.0) ; extra == 'test'
Requires-Dist: pytest ; extra == 'test'
Requires-Dist: zest.releaser[recommended] ; extra == 'test'
